chordsbert/README.md
chordsbert/TMIDIX.py
chordsbert/__init__.py
chordsbert/chordsbert.py
chordsbert/midi_to_colab_audio.py
chordsbert/sample_midis.py
chordsbert/x_transformer_2_3_1.py
chordsbert/artwork/Chords-BERT-Artwork-1.png
chordsbert/artwork/Chords-BERT-Artwork-2.png
chordsbert/artwork/Chords-BERT-Logo.png
chordsbert/artwork/Project-Los-Angeles.png
chordsbert/artwork/README.md
chordsbert/artwork/Tegridy-Code-2025.png
chordsbert/artwork/__init__.py
chordsbert/notebooks/__init__.py
chordsbert/output_samples/__init__.py
chordsbert/seed_midis/README.md
chordsbert/seed_midis/__init__.py
chordsbert/seed_midis/chords_bert_seed_midi_1.mid
chordsbert/seed_midis/chords_bert_seed_midi_2.mid
chordsbert/seed_midis/chords_bert_seed_midi_3.mid
chordsbert/seed_midis/chords_bert_seed_midi_4.mid
chordsbert/seed_midis/chords_bert_seed_midi_5.mid
chordsbert/seed_midis/chords_bert_seed_midi_6.mid
chordsbert-25.8.27.dist-info/licenses/LICENSE
chordsbert-25.8.27.dist-info/METADATA
chordsbert-25.8.27.dist-info/WHEEL
chordsbert-25.8.27.dist-info/top_level.txt
chordsbert-25.8.27.dist-info/RECORD
