Metadata-Version: 2.4
Name: chordsbert
Version: 25.8.27
Summary: BERT for working with MIDI chords
Author-email: Alex Lev <alexlev61@proton.me>
Maintainer-email: Alex Lev <alexlev61@proton.me>
License-Expression: Apache-2.0
Project-URL: Homepage, https://github.com/asigalov61/chordsbert
Project-URL: SoundCloud, https://soundcloud.com/aleksandr-sigalov-61/
Project-URL: Samples, https://github.com/asigalov61/chordsbert/tree/main/chordsbert/output_samples
Project-URL: Documentation, https://github.com/asigalov61/chordsbert
Project-URL: Issues, https://github.com/asigalov61/chordsbert/issues
Project-URL: Discussions, https://github.com/asigalov61/chordsbert/discussions
Project-URL: Dataset, https://huggingface.co/datasets/projectlosangeles/Godzilla-MIDI-Dataset
Project-URL: Models, https://huggingface.co/asigalov61/Chords-BERT
Keywords: MIDI,music,music ai,MIDI chords,Chords BERT,BERT,music chords,chords progressions,artificial intelligence,AI
Classifier: Development Status :: 5 - Production/Stable
Classifier: Intended Audience :: Science/Research
Classifier: Topic :: Multimedia :: Sound/Audio :: MIDI
Classifier: Operating System :: OS Independent
Classifier: Programming Language :: Python :: 3.6
Classifier: Programming Language :: Python :: 3.7
Classifier: Programming Language :: Python :: 3.8
Classifier: Programming Language :: Python :: 3.9
Classifier: Programming Language :: Python :: 3.10
Classifier: Programming Language :: Python :: 3.11
Classifier: Programming Language :: Python :: 3.12
Requires-Python: >=3.6
License-File: LICENSE
Requires-Dist: tqdm
Requires-Dist: ipywidgets
Requires-Dist: matplotlib
Requires-Dist: hf-transfer
Requires-Dist: huggingface_hub
Requires-Dist: torch
Requires-Dist: numpy==1.24.4
Requires-Dist: scipy
Requires-Dist: einops
Requires-Dist: einx
Requires-Dist: torch-summary
Dynamic: license-file
